neutron_vpnaas_dashboard/__init__.py
neutron_vpnaas_dashboard/version.py
neutron_vpnaas_dashboard/api/__init__.py
neutron_vpnaas_dashboard/api/vpn.py
neutron_vpnaas_dashboard/dashboards/__init__.py
neutron_vpnaas_dashboard/dashboards/project/__init__.py
neutron_vpnaas_dashboard/dashboards/project/vpn/__init__.py
neutron_vpnaas_dashboard/dashboards/project/vpn/forms.py
neutron_vpnaas_dashboard/dashboards/project/vpn/panel.py
neutron_vpnaas_dashboard/dashboards/project/vpn/tables.py
neutron_vpnaas_dashboard/dashboards/project/vpn/tabs.py
neutron_vpnaas_dashboard/dashboards/project/vpn/tests.py
neutron_vpnaas_dashboard/dashboards/project/vpn/urls.py
neutron_vpnaas_dashboard/dashboards/project/vpn/views.py
neutron_vpnaas_dashboard/dashboards/project/vpn/workflows.py
neutron_vpnaas_dashboard/dashboards/project/vpn/templates/vpn/_add_endpoint_group_help.html
neutron_vpnaas_dashboard/dashboards/project/vpn/templates/vpn/_add_ike_policy_help.html
neutron_vpnaas_dashboard/dashboards/project/vpn/templates/vpn/_add_ipsec_policy_help.html
neutron_vpnaas_dashboard/dashboards/project/vpn/templates/vpn/_add_vpn_service_help.html
neutron_vpnaas_dashboard/dashboards/project/vpn/templates/vpn/_endpointgroup_details.html
neutron_vpnaas_dashboard/dashboards/project/vpn/templates/vpn/_ikepolicy_details.html
neutron_vpnaas_dashboard/dashboards/project/vpn/templates/vpn/_ipsecpolicy_details.html
neutron_vpnaas_dashboard/dashboards/project/vpn/templates/vpn/_ipsecsiteconnection_details.html
neutron_vpnaas_dashboard/dashboards/project/vpn/templates/vpn/_update_endpointgroup.html
neutron_vpnaas_dashboard/dashboards/project/vpn/templates/vpn/_update_ikepolicy.html
neutron_vpnaas_dashboard/dashboards/project/vpn/templates/vpn/_update_ipsecpolicy.html
neutron_vpnaas_dashboard/dashboards/project/vpn/templates/vpn/_update_ipsecsiteconnection.html
neutron_vpnaas_dashboard/dashboards/project/vpn/templates/vpn/_update_vpnservice.html
neutron_vpnaas_dashboard-13.0.0.dist-info/AUTHORS
neutron_vpnaas_dashboard-13.0.0.dist-info/LICENSE
neutron_vpnaas_dashboard-13.0.0.dist-info/METADATA
neutron_vpnaas_dashboard-13.0.0.dist-info/WHEEL
neutron_vpnaas_dashboard-13.0.0.dist-info/pbr.json
neutron_vpnaas_dashboard-13.0.0.dist-info/top_level.txt
neutron_vpnaas_dashboard-13.0.0.dist-info/RECORD
